sqlite2duckdb/__init__.py
sqlite2duckdb/__main__.py
sqlite2duckdb/sqlite_to_duckdb.py
sqlite2duckdb-0.3.0.dist-info/METADATA
sqlite2duckdb-0.3.0.dist-info/WHEEL
sqlite2duckdb-0.3.0.dist-info/entry_points.txt
sqlite2duckdb-0.3.0.dist-info/licenses/LICENSE
sqlite2duckdb-0.3.0.dist-info/RECORD
